checkpwd/__init__.py
checkpwd/check_pwd.py
checkpwd/run.py
checkpwd-0.2.1.dist-info/LICENSE
checkpwd-0.2.1.dist-info/METADATA
checkpwd-0.2.1.dist-info/WHEEL
checkpwd-0.2.1.dist-info/entry_points.txt
checkpwd-0.2.1.dist-info/top_level.txt
checkpwd-0.2.1.dist-info/RECORD
